brewify/__init__.py
brewify/classes.py
brewify/core.py
brewify-0.1.6.dist-info/LICENSE
brewify-0.1.6.dist-info/METADATA
brewify-0.1.6.dist-info/WHEEL
brewify-0.1.6.dist-info/top_level.txt
brewify-0.1.6.dist-info/RECORD
