Metadata-Version: 2.1
Name: brewify
Version: 0.1.6
Summary: A Python library for interacting with various APIs including Google Search, IMDb, and Discord.
Home-page: https://github.com/opexdeveloper/brewify
Author: OPEX
Author-email: opexclaqz@gmail.com
Keywords: discord,utility,socials,info,api,wrapper
Classifier: Programming Language :: Python :: 3
Classifier: License :: OSI Approved :: MIT License
Classifier: Operating System :: OS Independent
Requires-Python: >=3.6
License-File: LICENSE
Requires-Dist: requests
Requires-Dist: pydantic
Requires-Dist: fastapi
Requires-Dist: loguru
Requires-Dist: geopy
Requires-Dist: country-converter
